pypuz/__init__.py
pypuz/file_types/__init__.py
pypuz/file_types/amuselabs.py
pypuz/file_types/cfp.py
pypuz/file_types/ipuz.py
pypuz/file_types/jpz.py
pypuz/file_types/puz.py
pypuz/pypuz.py
pypuz/test_files/3x.cfp
pypuz/test_files/3x.ipuz
pypuz/test_files/3x.jpz
pypuz/test_files/3x.puz
pypuz/test_files/3x.xml
pypuz-2025.9.24.dist-info/LICENSE
pypuz-2025.9.24.dist-info/LICENSE.txt
pypuz-2025.9.24.dist-info/METADATA
pypuz-2025.9.24.dist-info/WHEEL
pypuz-2025.9.24.dist-info/RECORD
