Metadata-Version: 2.1
Name: pypuz
Version: 2025.9.24
Summary: Reading and writing crossword files in Python
Author: Alex Boisvert
Author-email: crosswordnexus@gmail.com
Requires-Python: >=3.8,<4.0
Classifier: Programming Language :: Python :: 3
Classifier: Programming Language :: Python :: 3.8
Classifier: Programming Language :: Python :: 3.9
Classifier: Programming Language :: Python :: 3.10
Classifier: Programming Language :: Python :: 3.11
Classifier: Programming Language :: Python :: 3.12
Requires-Dist: Unidecode (>=1.4.0)
Requires-Dist: lxml (>=5.4.0)
